{
  "time_start": "14:37",
  "time_end": "20:38",
  "statistics": [
    {
      "Pennsylvania": [
        "Social Networking",
        "Social",
        "Single Professionals",
        "Singles",
        "Travel",
        "Dancing",
        "Dating and Relationships",
        "Weekend Getaways",
        "Single Parents",
        "Cruises"
      ]
    },
    {
      "Oregon": [
        "Philosophy",
        "Intellectual Discussion",
        "Critical Thinking",
        "Lectures",
        "Philosophy Discussions",
        "Debate"
      ]
    },
    {
      "Massachusetts": [
        "German Language",
        "Expat German",
        "Language & Culture",
        "German Culture",
        "Language Exchange",
        "Language Learning",
        "German Conversation",
        "Deutsch",
        "Learning Language",
        "German Expats",
        "language tandem",
        "German Language",
        "Expat German",
        "Language & Culture",
        "German Culture",
        "Language Exchange",
        "Language Learning",
        "German Conversation",
        "Deutsch",
        "Learning Language",
        "German Expats",
        "language tandem",
        "Business Intelligence",
        "Big Data",
        "Machine Learning",
        "Data Analytics",
        "Data Visualization",
        "Predictive Analytics",
        "Data Mining",
        "APIs",
        "DevOps",
        "Data Science",
        "Big Data Analytics",
        "Enterprise Application Integration",
        "API documentation",
        "German Language",
        "Expat German",
        "Language & Culture",
        "German Culture",
        "Language Exchange",
        "Language Learning",
        "German Conversation",
        "Deutsch",
        "Learning Language",
        "German Expats",
        "language tandem"
      ]
    },
    {
      "New York": [
        "Machine Learning",
        "BioInformatics",
        "Psychology",
        "Medical Imaging",
        "Artificial Intelligence Machine Learning Robotics",
        "Education & Technology",
        "Life Sciences",
        "Cognitive Science",
        "Biotechnology",
        "Brain",
        "Cognitive-neuro-biology",
        "Cognitive Neuroscience",
        "Applied Cognitive Science",
        "Near Infrared Spectroscopy",
        "brain-computer interface"
      ]
    },
    {
      "Florida": [
        "Powerful Women",
        "Women's Business Networking",
        "Business Referral Networking",
        "Professional Networking",
        "Women's Networking",
        "Women Small Business Owners",
        "Executive Coaching",
        "Small Business",
        "Professional Women",
        "Social",
        "Women's Social",
        "Self-Improvement",
        "Small Business Marketing Strategy",
        "Personal Growth and MBTI",
        "Self-Improvement",
        "Social Networking",
        "Professional",
        "Wine",
        "Women's Social",
        "Crafts",
        "Weekend Adventures",
        "Outdoor Adventures",
        "Spiritual Growth",
        "Women's Empowerment",
        "Self Exploration",
        "Creativity",
        "Knowledge Sharing",
        "Cocktails & Dining"
      ]
    },
    {
      "Illinois": [
        "Property Management",
        "Property Developing",
        "Making Money with Rental Property",
        "Hospitality & Tourism",
        "vacation rental properties",
        "Short Term Rental Income",
        "Airbnb",
        "Airbnb Host",
        "Environmental Awareness",
        "Green Living",
        "Vegetarian",
        "Weight Loss",
        "Sustainability",
        "Wellness",
        "Vegan Potlucks and Dineouts",
        "Healthy Living",
        "Environment",
        "Animal Welfare",
        "Vegan",
        "Whole Food Nutrition",
        "Nutrition",
        "Environmental Activism",
        "Plant-Based Nutrition"
      ]
    },
    {
      "District Of Columbia": [
        "Real Estate Investing Meetings",
        "Beginner Real Estate Investing",
        "First Time Real Estate Investing",
        "Real Estate Investment Education",
        "Startup Businesses",
        "Entrepreneurship",
        "Real Estate",
        "Business Strategy",
        "Real Estate Investing",
        "Real Estate Investors",
        "Real Estate Foreclosures",
        "Real Estate Networking",
        "Investing",
        "Cashflow",
        "Wholesale",
        "Real Estate Investing Meetings",
        "Beginner Real Estate Investing",
        "First Time Real Estate Investing",
        "Real Estate Investment Education",
        "Startup Businesses",
        "Entrepreneurship",
        "Real Estate",
        "Business Strategy",
        "Real Estate Investing",
        "Real Estate Investors",
        "Real Estate Foreclosures",
        "Real Estate Networking",
        "Investing",
        "Cashflow",
        "Wholesale"
      ]
    },
    {
      "South Carolina": [
        "Consciousness",
        "Meditation",
        "Self-Improvement",
        "Life Transformation",
        "Wellness",
        "Holistic Health",
        "Stress Relief",
        "Spiritual Growth",
        "Healthy Living",
        "Self Exploration",
        "Self-Empowerment"
      ]
    },
    {
      "Arizona": [
        "Fitness",
        "Bicycling",
        "Outdoors",
        "Exercise",
        "Road Cycling",
        "Cycling"
      ]
    },
    {
      "Georgia": [
        "Spades",
        "Spades League",
        "Playing Cards",
        "Spade Players",
        "Spade Games",
        "Cards",
        "Game Night",
        "Games",
        "Card Games",
        "Regular Spades",
        "Local Spades",
        "Spades players"
      ]
    },
    {
      "Virginia": [
        "Book Club"
      ]
    },
    {
      "New Jersey": [
        "Live Music",
        "Social",
        "Music",
        "Outdoors",
        "Fun Times",
        "Singles 30's-50's",
        "Concerts",
        "Eating, Drinking, Talking, Laughing, Etc",
        "Exploring New Restaurants",
        "Recreational Sports",
        "Coffee",
        "Dining Out",
        "Hiking and Bike Riding"
      ]
    },
    {
      "North Carolina": [
        "Mountains",
        "Backpacking",
        "Outdoor Adventures",
        "Adventure",
        "Fun Times",
        "Outdoors",
        "Social",
        "Camping",
        "Hiking",
        "Fitness",
        "Walking",
        "New In Town",
        "Rock Climbing",
        "Travel",
        "Mountaineering"
      ]
    }
  ]
}